MANIFEST.in
README.txt
setup.cfg
setup.py
docs/HISTORY.txt
horae/__init__.py
horae.app.egg-info/PKG-INFO
horae.app.egg-info/SOURCES.txt
horae.app.egg-info/dependency_links.txt
horae.app.egg-info/entry_points.txt
horae.app.egg-info/namespace_packages.txt
horae.app.egg-info/not-zip-safe
horae.app.egg-info/requires.txt
horae.app.egg-info/top_level.txt
horae/app/__init__.py
horae/app/app.py
horae/app/configure.zcml
horae/app/tests/__init__.py
horae/app/tests/app.txt
horae/app/tests/ftesting.zcml
horae/app/tests/test_horae.py
horae/app/tests/tests.py