Metadata-Version: 1.0
Name: horae.app
Version: 1.0a1
Summary: Provides the Horae resource planning system as a Grok application
Home-page: UNKNOWN
Author: Simon Kaeser
Author-email: skaeser@gmail.com
License: GPL
Platform: UNKNOWN
Classifier: Programming Language :: Python
Classifier: Topic :: Software Development :: Libraries :: Python Modules
